{
    "created_time": "2025-05-30T02:36:45Z",
    "files": [
        {
            "attachment_folder": "",
            "created_time": "2025-05-30T02:36:45Z",
            "id": "1251",
            "modified_time": "2025-05-30T02:36:45Z",
            "name": "700E4F39BC05364B.asc",
            "signature": "7803583149081434557",
            "tags": [
            ]
        },
        {
            "attachment_folder": "",
            "created_time": "2025-05-30T02:36:45Z",
            "id": "1252",
            "modified_time": "2025-05-30T02:36:45Z",
            "name": "about.html",
            "signature": "8783465351954897341",
            "tags": [
            ]
        },
        {
            "attachment_folder": "",
            "created_time": "2025-05-30T02:36:45Z",
            "id": "1253",
            "modified_time": "2025-05-30T02:36:45Z",
            "name": "about.ini",
            "signature": "11151729087976380861",
            "tags": [
            ]
        },
        {
            "attachment_folder": "",
            "created_time": "2025-05-30T02:36:45Z",
            "id": "1254",
            "modified_time": "2025-05-30T02:36:45Z",
            "name": "about.mappings",
            "signature": "9393029822390278589",
            "tags": [
            ]
        },
        {
            "attachment_folder": "",
            "created_time": "2025-05-30T02:36:45Z",
            "id": "1255",
            "modified_time": "2025-05-30T02:36:45Z",
            "name": "about.properties",
            "signature": "1819420600137488829",
            "tags": [
            ]
        },
        {
            "attachment_folder": "",
            "created_time": "2025-05-30T02:36:45Z",
            "id": "1256",
            "modified_time": "2025-05-30T02:36:45Z",
            "name": "book.css",
            "signature": "827234037515491773",
            "tags": [
            ]
        },
        {
            "attachment_folder": "",
            "created_time": "2025-05-30T02:36:45Z",
            "id": "1257",
            "modified_time": "2025-05-30T02:36:45Z",
            "name": "disabled_book.css",
            "signature": "2808595067835062717",
            "tags": [
            ]
        },
        {
            "attachment_folder": "",
            "created_time": "2025-05-30T02:36:45Z",
            "id": "1258",
            "modified_time": "2025-05-30T02:36:45Z",
            "name": "eclipse1024.png",
            "signature": "9157579251367090621",
            "tags": [
            ]
        },
        {
            "attachment_folder": "",
            "created_time": "2025-05-30T02:36:45Z",
            "id": "1259",
            "modified_time": "2025-05-30T02:36:45Z",
            "name": "eclipse128.png",
            "signature": "15129592334263065021",
            "tags": [
            ]
        },
        {
            "attachment_folder": "",
            "created_time": "2025-05-30T02:36:45Z",
            "id": "1260",
            "modified_time": "2025-05-30T02:36:45Z",
            "name": "eclipse16.png",
            "signature": "9813350560520804797",
            "tags": [
            ]
        },
        {
            "attachment_folder": "",
            "created_time": "2025-05-30T02:36:45Z",
            "id": "1261",
            "modified_time": "2025-05-30T02:36:45Z",
            "name": "eclipse22.png",
            "signature": "4689905526484048317",
            "tags": [
            ]
        },
        {
            "attachment_folder": "",
            "created_time": "2025-05-30T02:36:45Z",
            "id": "1262",
            "modified_time": "2025-05-30T02:36:45Z",
            "name": "eclipse24.png",
            "signature": "2844220494410488253",
            "tags": [
            ]
        },
        {
            "attachment_folder": "",
            "created_time": "2025-05-30T02:36:45Z",
            "id": "1263",
            "modified_time": "2025-05-30T02:36:45Z",
            "name": "eclipse256.png",
            "signature": "15977165930689534397",
            "tags": [
            ]
        },
        {
            "attachment_folder": "",
            "created_time": "2025-05-30T02:36:45Z",
            "id": "1264",
            "modified_time": "2025-05-30T02:36:45Z",
            "name": "eclipse32.png",
            "signature": "3105390665336953277",
            "tags": [
            ]
        },
        {
            "attachment_folder": "",
            "created_time": "2025-05-30T02:36:45Z",
            "id": "1265",
            "modified_time": "2025-05-30T02:36:45Z",
            "name": "eclipse48.png",
            "signature": "8791613944297494973",
            "tags": [
            ]
        },
        {
            "attachment_folder": "",
            "created_time": "2025-05-30T02:36:45Z",
            "id": "1266",
            "modified_time": "2025-05-30T02:36:45Z",
            "name": "eclipse512.png",
            "signature": "10384390681844586941",
            "tags": [
            ]
        },
        {
            "attachment_folder": "",
            "created_time": "2025-05-30T02:36:45Z",
            "id": "1267",
            "modified_time": "2025-05-30T02:36:45Z",
            "name": "eclipse64.png",
            "signature": "3618538832283638205",
            "tags": [
            ]
        },
        {
            "attachment_folder": "",
            "created_time": "2025-05-30T02:36:45Z",
            "id": "1268",
            "modified_time": "2025-05-30T02:36:45Z",
            "name": "eclipse_lg.png",
            "signature": "10246566684554500541",
            "tags": [
            ]
        },
        {
            "attachment_folder": "",
            "created_time": "2025-05-30T02:36:45Z",
            "id": "1269",
            "modified_time": "2025-05-30T02:36:45Z",
            "name": "eclipse_lg@2x.png",
            "signature": "15290492915956652477",
            "tags": [
            ]
        },
        {
            "attachment_folder": "",
            "created_time": "2025-05-30T02:36:45Z",
            "id": "1270",
            "modified_time": "2025-05-30T02:36:45Z",
            "name": "helpData.xml",
            "signature": "6121090385876425149",
            "tags": [
            ]
        },
        {
            "attachment_folder": "",
            "created_time": "2025-05-30T02:36:46Z",
            "id": "1316",
            "modified_time": "2025-05-30T02:36:46Z",
            "name": "intro-eclipse.svg",
            "signature": "12173561761143265726",
            "tags": [
            ]
        },
        {
            "attachment_folder": "",
            "created_time": "2025-05-30T02:36:46Z",
            "id": "1317",
            "modified_time": "2025-05-30T02:36:46Z",
            "name": "introData.xml",
            "signature": "12278285905771960766",
            "tags": [
            ]
        },
        {
            "attachment_folder": "",
            "created_time": "2025-05-30T02:36:46Z",
            "id": "1318",
            "modified_time": "2025-05-30T02:36:46Z",
            "name": "LegacyIDE.e4xmi",
            "signature": "13122721538962430398",
            "tags": [
            ]
        },
        {
            "attachment_folder": "",
            "created_time": "2025-05-30T02:36:46Z",
            "id": "1319",
            "modified_time": "2025-05-30T02:36:46Z",
            "name": "macosx_narrow_book.css",
            "signature": "16545994577647573438",
            "tags": [
            ]
        },
        {
            "attachment_folder": "",
            "created_time": "2025-05-30T02:36:46Z",
            "id": "1324",
            "modified_time": "2025-05-30T02:36:46Z",
            "name": "narrow_book.css",
            "signature": "3864575737482254782",
            "tags": [
            ]
        },
        {
            "attachment_folder": "",
            "created_time": "2025-05-30T02:36:46Z",
            "id": "1327",
            "modified_time": "2025-05-30T02:36:46Z",
            "name": "platform.jar",
            "signature": "9431646899845798334",
            "tags": [
            ]
        },
        {
            "attachment_folder": "",
            "created_time": "2025-05-30T02:36:46Z",
            "id": "1328",
            "modified_time": "2025-05-30T02:36:46Z",
            "name": "plugin.properties",
            "signature": "12598730061357062590",
            "tags": [
            ]
        },
        {
            "attachment_folder": "",
            "created_time": "2025-05-30T02:36:46Z",
            "id": "1329",
            "modified_time": "2025-05-30T02:36:46Z",
            "name": "plugin.xml",
            "signature": "8393035747958528446",
            "tags": [
            ]
        },
        {
            "attachment_folder": "",
            "created_time": "2025-05-30T02:36:46Z",
            "id": "1330",
            "modified_time": "2025-05-30T02:36:46Z",
            "name": "plugin_customization.ini",
            "signature": "13878349690991876542",
            "tags": [
            ]
        },
        {
            "attachment_folder": "",
            "created_time": "2025-05-30T02:36:46Z",
            "id": "1331",
            "modified_time": "2025-05-30T02:36:46Z",
            "name": "plugin_customization.properties",
            "signature": "16400883579929303486",
            "tags": [
            ]
        },
        {
            "attachment_folder": "",
            "created_time": "2025-05-30T02:36:46Z",
            "id": "1332",
            "modified_time": "2025-05-30T02:36:46Z",
            "name": "splash.png",
            "signature": "2100152276922997182",
            "tags": [
            ]
        }
    ],
    "folders": [
        {
            "name": "images"
        },
        {
            "name": "intro"
        },
        {
            "name": "META-INF"
        },
        {
            "name": "org.eclipse.ui.intro.universal.solstice"
        }
    ],
    "id": "1250",
    "modified_time": "2025-05-30T02:36:45Z",
    "signature": "3073475343180962237",
    "version": 3
}
